[
  {
    "first_name": "Stipe", 
    "last_name": "Pletikosa", 
    "name": "Stipe Pletikosa", 
    "short_name": "Pletikosa", 
    "real_position": "Goalkeeper", 
    "club": "FC Rostov", 
    "country": "Croatia", 
    "first_nationality": "Croatia", 
    "join_date": "2000-03-29", 
    "weight": "82", 
    "height": "193", 
    "position_wc": "G", 
    "team_id": 535, 
    "birth_place": "Split", 
    "caps": "111", 
    "birth_date": "1979-01-08", 
    "position": "Goalkeeper", 
    "real_position_side": "Unknown", 
    "jersey_num": "1", 
    "id": 7810, 
    "goals": "0"
  }, 
  {
    "last_name": "Olic", 
    "weight": "85", 
    "first_nationality": "Croatia", 
    "height": "182", 
    "position_wc": "M-L", 
    "team_id": 535, 
    "preferred_foot": "Left", 
    "id": 13139, 
    "first_name": "Ivica", 
    "short_name": "Olic", 
    "real_position": "Striker", 
    "club": "VfL Wolfsburg", 
    "caps": "92", 
    "goals": "18", 
    "position": "Forward", 
    "real_position_side": "Left/Centre", 
    "jersey_num": "18", 
    "name": "Ivica Olic", 
    "country": "Croatia", 
    "join_date": "2002-04-01", 
    "birth_date": "1979-09-14", 
    "birth_place": "Davor"
  }, 
  {
    "first_name": "Darijo", 
    "last_name": "Srna", 
    "name": "Darijo Srna", 
    "short_name": "Srna", 
    "real_position": "Wing Back", 
    "club": "Shakhtar Donetsk", 
    "country": "Croatia", 
    "first_nationality": "Croatia", 
    "join_date": "2002-08-01", 
    "weight": "78", 
    "height": "182", 
    "position_wc": "D-R", 
    "team_id": 535, 
    "birth_place": "Metkovic", 
    "caps": "112", 
    "birth_date": "1982-05-01", 
    "position": "Defender", 
    "real_position_side": "Right", 
    "jersey_num": "11", 
    "id": 17347, 
    "goals": "21"
  }, 
  {
    "last_name": "Pranjic", 
    "weight": "70", 
    "first_nationality": "Yugoslavia", 
    "height": "171", 
    "position_wc": "D-L", 
    "team_id": 535, 
    "preferred_foot": "Left", 
    "id": 28103, 
    "first_name": "Danijel", 
    "short_name": "Pranjic", 
    "real_position": "Full Back", 
    "club": "Panathinaikos", 
    "caps": "50", 
    "goals": "0", 
    "position": "Defender", 
    "real_position_side": "Left", 
    "jersey_num": "3", 
    "name": "Danijel Pranjic", 
    "country": "Croatia", 
    "join_date": "2002-08-01", 
    "birth_date": "1981-12-02", 
    "birth_place": "Na\u0161ice"
  }, 
  {
    "last_name": "Rakitic", 
    "weight": "72", 
    "first_nationality": "Switzerland", 
    "height": "184", 
    "position_wc": "M", 
    "team_id": 535, 
    "preferred_foot": "Right", 
    "id": 34703, 
    "first_name": "Ivan", 
    "short_name": "Rakitic", 
    "real_position": "Attacking Midfielder", 
    "club": "Sevilla", 
    "caps": "62", 
    "goals": "9", 
    "position": "Midfielder", 
    "real_position_side": "Left/Centre/Right", 
    "jersey_num": "7", 
    "name": "Ivan Rakitic", 
    "country": "Croatia", 
    "join_date": "2007-09-05", 
    "birth_date": "1988-03-10", 
    "birth_place": "Mohlin"
  }, 
  {
    "first_name": "Luka", 
    "last_name": "Modric", 
    "name": "Luka Modric", 
    "short_name": "Modric", 
    "real_position": "Attacking Midfielder", 
    "club": "Real Madrid", 
    "country": "Croatia", 
    "first_nationality": "Croatia", 
    "join_date": "2002-08-01", 
    "weight": "67", 
    "height": "175", 
    "position_wc": "M", 
    "team_id": 535, 
    "birth_place": "Zadar", 
    "caps": "75", 
    "birth_date": "1985-09-09", 
    "position": "Midfielder", 
    "real_position_side": "Left/Centre/Right", 
    "jersey_num": "10", 
    "id": 37055, 
    "goals": "8"
  }, 
  {
    "last_name": "Lovren", 
    "weight": "84", 
    "first_nationality": "Bosnia and Herzegovina", 
    "height": "188", 
    "position_wc": "D", 
    "team_id": 535, 
    "preferred_foot": "Both", 
    "id": 38454, 
    "first_name": "Dejan", 
    "short_name": "Lovren", 
    "real_position": "Full Back", 
    "club": "Southampton", 
    "caps": "25", 
    "goals": "2", 
    "position": "Defender", 
    "real_position_side": "Centre/Right", 
    "jersey_num": "6", 
    "name": "Dejan Lovren", 
    "country": "Croatia", 
    "join_date": "2009-08-01", 
    "birth_date": "1989-07-05", 
    "birth_place": "Zenica"
  }, 
  {
    "first_name": "Vedran", 
    "last_name": "Corluka", 
    "name": "Vedran Corluka", 
    "short_name": "Corluka", 
    "real_position": "Full Back", 
    "club": "Lokomotiv Moscow", 
    "country": "Croatia", 
    "first_nationality": "Yugoslavia", 
    "join_date": "2002-08-01", 
    "weight": "82", 
    "height": "193", 
    "position_wc": "D", 
    "team_id": 535, 
    "birth_place": "Derventa", 
    "caps": "72", 
    "birth_date": "1986-02-05", 
    "position": "Defender", 
    "real_position_side": "Centre/Right", 
    "jersey_num": "5", 
    "id": 38462, 
    "goals": "4"
  }, 
  {
    "last_name": "da Silva", 
    "weight": "72", 
    "first_nationality": "Brazil", 
    "height": "177", 
    "position_wc": "M-L", 
    "team_id": 535, 
    "known_name": "Eduardo", 
    "birth_place": "Rio de Janeiro", 
    "id": 38470, 
    "first_name": "Eduardo", 
    "short_name": "Eduardo", 
    "real_position": "Striker", 
    "club": "Shakhtar Donetsk", 
    "caps": "63", 
    "goals": "29", 
    "real_position_side": "Centre", 
    "jersey_num": "22", 
    "name": "Eduardo", 
    "country": "Croatia", 
    "join_date": "2002-08-01", 
    "birth_date": "1983-02-25", 
    "position": "Forward"
  }, 
  {
    "first_name": "Ognjen", 
    "last_name": "Vukojevic", 
    "name": "Ognjen Vukojevic", 
    "short_name": "Vukojevic", 
    "real_position": "Defensive Midfielder", 
    "club": "Dynamo Kyiv", 
    "country": "Croatia", 
    "first_nationality": "Yugoslavia", 
    "join_date": "2007-11-01", 
    "weight": "76", 
    "height": "183", 
    "position_wc": null, 
    "team_id": 535, 
    "birth_place": "Bjelovar", 
    "caps": "55", 
    "birth_date": "1983-12-20", 
    "position": "Midfielder", 
    "real_position_side": "Centre", 
    "jersey_num": "8", 
    "id": 38472, 
    "goals": "4"
  }, 
  {
    "last_name": "Perisic", 
    "weight": "81", 
    "first_nationality": "Croatia", 
    "height": "187", 
    "position_wc": "M-R", 
    "team_id": 535, 
    "preferred_foot": "Right", 
    "id": 45034, 
    "first_name": "Ivan", 
    "short_name": "Perisic", 
    "real_position": "Attacking Midfielder", 
    "club": "VfL Wolfsburg", 
    "caps": "29", 
    "goals": "3", 
    "position": "Midfielder", 
    "real_position_side": "Left/Centre/Right", 
    "jersey_num": "4", 
    "name": "Ivan Perisic", 
    "country": "Croatia", 
    "join_date": "2011-02-01", 
    "birth_date": "1989-02-02", 
    "birth_place": "Split"
  }, 
  {
    "last_name": "Mandzukic", 
    "weight": "84", 
    "first_nationality": "Croatia", 
    "height": "187", 
    "position_wc": "F", 
    "team_id": 535, 
    "preferred_foot": "Right", 
    "id": 46197, 
    "first_name": "Mario", 
    "short_name": "Mandzukic", 
    "real_position": "Striker", 
    "club": "FC Bayern M\u00fcnchen", 
    "caps": "50", 
    "goals": "13", 
    "position": "Forward", 
    "real_position_side": "Centre", 
    "jersey_num": "17", 
    "name": "Mario Mandzukic", 
    "country": "Croatia", 
    "join_date": "2007-11-12", 
    "birth_date": "1986-05-21", 
    "birth_place": "Slavonski Brod"
  }, 
  {
    "last_name": "Cruz Campos", 
    "weight": "77", 
    "first_nationality": "Brazil", 
    "height": "178", 
    "position_wc": "M", 
    "team_id": 535, 
    "known_name": "Sammir", 
    "preferred_foot": "Right", 
    "id": 46198, 
    "first_name": "Jorge Sammir", 
    "short_name": "Sammir", 
    "real_position": "Attacking Midfielder", 
    "club": "Getafe", 
    "caps": "6", 
    "goals": "0", 
    "position": "Midfielder", 
    "real_position_side": "Centre", 
    "jersey_num": "19", 
    "name": "Sammir", 
    "country": "Croatia", 
    "join_date": "2012-10-09", 
    "birth_date": "1987-04-23", 
    "birth_place": "Itabuna"
  }, 
  {
    "first_name": "Gordon", 
    "last_name": "Schildenfeld", 
    "name": "Gordon Schildenfeld", 
    "short_name": "Schildenfeld", 
    "real_position": "Central Defender", 
    "club": "Panathinaikos", 
    "country": "Croatia", 
    "first_nationality": "Croatia", 
    "join_date": "2009-11-01", 
    "weight": "89", 
    "height": "191", 
    "position_wc": null, 
    "team_id": 535, 
    "birth_place": "Sibenik", 
    "caps": "21", 
    "birth_date": "1985-03-18", 
    "position": "Defender", 
    "real_position_side": "Centre", 
    "jersey_num": "13", 
    "id": 46203, 
    "goals": "0"
  }, 
  {
    "last_name": "Badelj", 
    "weight": "76", 
    "first_nationality": "Croatia", 
    "height": "186", 
    "position_wc": null, 
    "team_id": 535, 
    "preferred_foot": "Right", 
    "id": 56999, 
    "first_name": "Milan", 
    "short_name": "Badelj", 
    "real_position": "Central Midfielder", 
    "club": "Hamburger SV", 
    "caps": "9", 
    "goals": "1", 
    "position": "Midfielder", 
    "real_position_side": "Left/Centre/Right", 
    "jersey_num": "15", 
    "name": "Milan Badelj", 
    "country": "Croatia", 
    "join_date": "2010-05-01", 
    "birth_date": "1989-02-25", 
    "birth_place": "Zagreb"
  }, 
  {
    "first_name": "Danijel", 
    "last_name": "Subasic", 
    "name": "Danijel Subasic", 
    "short_name": "Subasic", 
    "real_position": "Goalkeeper", 
    "club": "Monaco", 
    "country": "Croatia", 
    "first_nationality": "Croatia", 
    "join_date": "2009-03-20", 
    "weight": "84", 
    "height": "192", 
    "position_wc": null, 
    "team_id": 535, 
    "birth_place": "Zadar", 
    "caps": "6", 
    "birth_date": "1984-10-27", 
    "position": "Goalkeeper", 
    "real_position_side": "Unknown", 
    "jersey_num": "23", 
    "id": 60582, 
    "goals": "0"
  }, 
  {
    "first_name": "Nikica", 
    "last_name": "Jelavic", 
    "name": "Nikica Jelavic", 
    "short_name": "Jelavic", 
    "real_position": "Striker", 
    "club": "Hull City", 
    "country": "Croatia", 
    "first_nationality": "Bosnia and Herzegovina", 
    "join_date": "2009-10-14", 
    "weight": "84", 
    "height": "187", 
    "position_wc": "F", 
    "team_id": 535, 
    "birth_place": "Capljina", 
    "caps": "33", 
    "birth_date": "1985-08-27", 
    "position": "Forward", 
    "real_position_side": "Centre", 
    "jersey_num": "9", 
    "id": 62419, 
    "goals": "6"
  }, 
  {
    "last_name": "Vrsaljko", 
    "weight": "75", 
    "first_nationality": "Croatia", 
    "height": "183", 
    "position_wc": "D-L", 
    "team_id": 535, 
    "preferred_foot": "Right", 
    "id": 68353, 
    "first_name": "Sime", 
    "short_name": "Vrsaljko", 
    "real_position": "Full Back", 
    "club": "Genoa", 
    "caps": "7", 
    "goals": "0", 
    "position": "Defender", 
    "real_position_side": "Right", 
    "jersey_num": "2", 
    "name": "Sime Vrsaljko", 
    "country": "Croatia", 
    "join_date": "2010-11-02", 
    "birth_date": "1992-01-10", 
    "birth_place": "Rijeka"
  }, 
  {
    "first_name": "Domagoj", 
    "last_name": "Vida", 
    "name": "Domagoj Vida", 
    "short_name": "Vida", 
    "real_position": "Full Back", 
    "club": "Dynamo Kyiv", 
    "country": "Croatia", 
    "first_nationality": "Croatia", 
    "join_date": "2010-05-01", 
    "weight": "73", 
    "height": "184", 
    "position_wc": null, 
    "team_id": 535, 
    "birth_place": "Osijek", 
    "caps": "23", 
    "birth_date": "1989-04-29", 
    "position": "Defender", 
    "real_position_side": "Centre/Right", 
    "jersey_num": "21", 
    "id": 68394, 
    "goals": "1"
  }, 
  {
    "last_name": "Kovacic", 
    "weight": "63", 
    "first_nationality": "Austria", 
    "height": "181", 
    "position_wc": "M", 
    "team_id": 535, 
    "preferred_foot": "Mostly Right", 
    "id": 91651, 
    "first_name": "Mateo", 
    "short_name": "Kovacic", 
    "real_position": "Attacking Midfielder", 
    "club": "Internazionale", 
    "caps": "10", 
    "goals": "0", 
    "position": "Midfielder", 
    "real_position_side": "Left/Centre/Right", 
    "jersey_num": "20", 
    "name": "Mateo Kovacic", 
    "country": "Croatia", 
    "join_date": "2012-08-01", 
    "birth_date": "1994-05-06", 
    "birth_place": "Linz"
  }, 
  {
    "first_name": "Marcelo", 
    "last_name": "Brozovic", 
    "name": "Marcelo Brozovic", 
    "short_name": "Brozovic", 
    "real_position": "Central Midfielder", 
    "club": "Dinamo Zagreb", 
    "country": "Croatia", 
    "first_nationality": "Croatia", 
    "join_date": "2014-05-13", 
    "weight": "65", 
    "height": "180", 
    "position_wc": "M", 
    "team_id": 535, 
    "birth_place": "Zagreb", 
    "caps": "1", 
    "birth_date": "1992-11-16", 
    "position": "Midfielder", 
    "real_position_side": "Centre", 
    "jersey_num": "14", 
    "id": 94425, 
    "goals": "0"
  }, 
  {
    "last_name": "Rebic", 
    "weight": "80", 
    "first_nationality": "Croatia", 
    "height": "185", 
    "position_wc": "F", 
    "team_id": 535, 
    "preferred_foot": "Right", 
    "id": 98456, 
    "first_name": "Ante", 
    "short_name": "Rebic", 
    "real_position": "Striker", 
    "club": "Fiorentina", 
    "caps": "5", 
    "goals": "1", 
    "position": "Forward", 
    "real_position_side": "Centre", 
    "jersey_num": "16", 
    "name": "Ante Rebic", 
    "country": "Croatia", 
    "join_date": "2013-08-01", 
    "birth_date": "1993-09-21", 
    "birth_place": "Split"
  }, 
  {
    "first_name": "Oliver", 
    "last_name": "Zelenika", 
    "name": "Oliver Zelenika", 
    "short_name": "Zelenika", 
    "real_position": "Goalkeeper", 
    "club": "Lokomotiva Zagreb", 
    "country": "Croatia", 
    "first_nationality": "Croatia", 
    "join_date": "2014-05-13", 
    "weight": "82", 
    "height": "192", 
    "position_wc": null, 
    "team_id": 535, 
    "birth_place": "Zagreb", 
    "caps": "0", 
    "birth_date": "1993-05-14", 
    "position": "Goalkeeper", 
    "real_position_side": "Unknown", 
    "jersey_num": "12", 
    "id": 104514, 
    "goals": "0"
  }, 
  {
    "first_name": "Rafael", 
    "last_name": "M\u00e1rquez", 
    "name": "Rafael M\u00e1rquez", 
    "short_name": "M\u00e1rquez", 
    "real_position": "Central Defender", 
    "club": "Le\u00f3n", 
    "country": "Mexico", 
    "first_nationality": "Mexico", 
    "join_date": "1997-02-01", 
    "weight": "76", 
    "height": "183", 
    "position_wc": "D", 
    "team_id": 659, 
    "birth_place": "Zamora", 
    "caps": "120", 
    "birth_date": "1979-02-13", 
    "position": "Defender", 
    "real_position_side": "Centre", 
    "jersey_num": "4", 
    "id": 6685, 
    "goals": "15"
  }, 
  {
    "last_name": "Salcido", 
    "weight": "72", 
    "first_nationality": "Mexico", 
    "height": "176", 
    "position_wc": "M-R", 
    "team_id": 659, 
    "birth_place": "Ocotl\u00e1n", 
    "id": 20322, 
    "first_name": "Carlos", 
    "middle_name": "Arnoldo", 
    "short_name": "Salcido", 
    "real_position": "Full Back", 
    "club": "Guadalajara", 
    "caps": "120", 
    "goals": "10", 
    "real_position_side": "Left", 
    "jersey_num": "3", 
    "name": "Carlos Salcido", 
    "country": "Mexico", 
    "join_date": "2004-09-01", 
    "birth_date": "1980-04-02", 
    "position": "Defender"
  }, 
  {
    "first_name": "Jose de Jes\u00fas", 
    "last_name": "Corona", 
    "name": "Jose de Jes\u00fas Corona", 
    "short_name": "Corona", 
    "real_position": "Goalkeeper", 
    "club": "Cruz Azul", 
    "country": "Mexico", 
    "first_nationality": "Mexico", 
    "join_date": "2005-01-01", 
    "weight": "82", 
    "height": "178", 
    "position_wc": null, 
    "team_id": 659, 
    "birth_place": "Guadalajara", 
    "caps": "33", 
    "birth_date": "1981-01-26", 
    "position": "Goalkeeper", 
    "real_position_side": "Unknown", 
    "jersey_num": "1", 
    "id": 20335, 
    "goals": "0"
  }, 
  {
    "first_name": "Francisco Javier", 
    "last_name": "Rodr\u00edguez", 
    "name": "Francisco Javier Rodr\u00edguez", 
    "short_name": "Rodr\u00edguez", 
    "real_position": "Central Defender", 
    "club": "Am\u00e9rica", 
    "country": "Mexico", 
    "first_nationality": "Mexico", 
    "join_date": "2004-02-01", 
    "weight": "84", 
    "height": "191", 
    "position_wc": "D", 
    "team_id": 659, 
    "birth_place": "Mazatl\u00e1n", 
    "caps": "93", 
    "birth_date": "1981-10-20", 
    "position": "Defender", 
    "real_position_side": "Centre", 
    "jersey_num": "2", 
    "id": 33360, 
    "goals": "1"
  }, 
  {
    "first_name": "Guillermo", 
    "last_name": "Ochoa", 
    "name": "Guillermo Ochoa", 
    "short_name": "Ochoa", 
    "real_position": "Goalkeeper", 
    "club": "Ajaccio", 
    "country": "Mexico", 
    "first_nationality": "Mexico", 
    "join_date": "2005-01-01", 
    "weight": "72", 
    "height": "183", 
    "position_wc": "G", 
    "team_id": 659, 
    "birth_place": "Guadalajara", 
    "caps": "57", 
    "birth_date": "1985-07-13", 
    "position": "Goalkeeper", 
    "real_position_side": "Unknown", 
    "jersey_num": "13", 
    "id": 33376, 
    "goals": "0"
  }, 
  {
    "last_name": "Guardado", 
    "weight": "67", 
    "first_nationality": "Mexico", 
    "height": "169", 
    "position_wc": "M-L", 
    "team_id": 659, 
    "preferred_foot": "Left", 
    "id": 37064, 
    "first_name": "Andr\u00e9s", 
    "short_name": "Guardado", 
    "real_position": "Winger", 
    "club": "Valencia CF", 
    "caps": "102", 
    "goals": "14", 
    "position": "Midfielder", 
    "real_position_side": "Left", 
    "jersey_num": "18", 
    "name": "Andr\u00e9s Guardado", 
    "country": "Mexico", 
    "join_date": "2005-12-01", 
    "birth_date": "1986-09-28", 
    "birth_place": "Guadalajara"
  }, 
  {
    "last_name": "dos Santos", 
    "weight": "71", 
    "first_nationality": "Mexico", 
    "height": "179", 
    "position_wc": "F", 
    "team_id": 659, 
    "preferred_foot": "Left", 
    "id": 40275, 
    "first_name": "Giovani", 
    "short_name": "dos Santos", 
    "real_position": "Second Striker", 
    "club": "Villarreal", 
    "caps": "74", 
    "goals": "15", 
    "position": "Forward", 
    "real_position_side": "Left/Centre/Right", 
    "jersey_num": "10", 
    "name": "Giovani dos Santos", 
    "country": "Mexico", 
    "join_date": "2008-01-01", 
    "birth_date": "1989-05-11", 
    "birth_place": "Monterrey"
  }, 
  {
    "first_name": "Alfredo", 
    "last_name": "Talavera", 
    "name": "Alfredo Talavera", 
    "short_name": "Talavera", 
    "real_position": "Goalkeeper", 
    "club": "Toluca", 
    "country": "Mexico", 
    "first_nationality": "Mexico", 
    "join_date": "2011-06-02", 
    "weight": "85", 
    "height": "188", 
    "position_wc": null, 
    "team_id": 659, 
    "birth_place": "La Barca", 
    "caps": "14", 
    "birth_date": "1982-09-18", 
    "position": "Goalkeeper", 
    "real_position_side": "Unknown", 
    "jersey_num": "12", 
    "id": 43013, 
    "goals": "0"
  }, 
  {
    "last_name": "Hern\u00e1ndez", 
    "weight": "62", 
    "first_nationality": "Mexico", 
    "height": "173", 
    "position_wc": "F", 
    "team_id": 659, 
    "preferred_foot": "Right", 
    "id": 43020, 
    "first_name": "Javier", 
    "middle_name": "Balc\u00e1zar", 
    "short_name": "Hern\u00e1ndez", 
    "real_position": "Striker", 
    "club": "Manchester United", 
    "caps": "62", 
    "goals": "35", 
    "position": "Forward", 
    "real_position_side": "Centre", 
    "jersey_num": "14", 
    "name": "Javier Hern\u00e1ndez", 
    "country": "Mexico", 
    "join_date": "2009-09-01", 
    "birth_date": "1988-06-01", 
    "birth_place": "Guadalajara"
  }, 
  {
    "last_name": "Aguilar", 
    "weight": "65", 
    "first_nationality": "Mexico", 
    "height": "178", 
    "position_wc": "D-R", 
    "team_id": 659, 
    "preferred_foot": "Right", 
    "id": 43106, 
    "first_name": "Paul", 
    "middle_name": "Nicol\u00e1s", 
    "short_name": "Aguilar", 
    "real_position": "Wing Back", 
    "club": "Am\u00e9rica", 
    "caps": "28", 
    "goals": "3", 
    "position": "Defender", 
    "real_position_side": "Right", 
    "jersey_num": "22", 
    "name": "Paul Aguilar", 
    "country": "Mexico", 
    "join_date": "2010-01-01", 
    "birth_date": "1986-03-06", 
    "birth_place": "Concordia"
  }, 
  {
    "last_name": "Moreno", 
    "weight": "81", 
    "first_nationality": "Mexico", 
    "height": "184", 
    "position_wc": "D", 
    "team_id": 659, 
    "known_name": "H\u00e9ctor Moreno", 
    "preferred_foot": "Left", 
    "id": 49656, 
    "first_name": "H\u00e9ctor", 
    "middle_name": "Alfredo", 
    "short_name": "H\u00e9ctor Moreno", 
    "real_position": "Central Defender", 
    "club": "Espanyol", 
    "caps": "53", 
    "goals": "1", 
    "position": "Defender", 
    "real_position_side": "Centre", 
    "jersey_num": "15", 
    "name": "H\u00e9ctor Moreno", 
    "country": "Mexico", 
    "join_date": "2007-03-01", 
    "birth_date": "1988-01-17", 
    "birth_place": "Culiac\u00e1n"
  }, 
  {
    "first_name": "Oribe", 
    "last_name": "Peralta", 
    "name": "Oribe Peralta", 
    "short_name": "Peralta", 
    "real_position": "Striker", 
    "club": "Am\u00e9rica", 
    "country": "Mexico", 
    "first_nationality": "Mexico", 
    "join_date": "2005-01-01", 
    "weight": "70", 
    "height": "178", 
    "position_wc": "F", 
    "team_id": 659, 
    "birth_place": "Torre\u00f3n", 
    "caps": "28", 
    "birth_date": "1984-01-12", 
    "position": "Forward", 
    "real_position_side": "Centre", 
    "jersey_num": "19", 
    "id": 53515, 
    "goals": "16"
  }, 
  {
    "last_name": "Fabi\u00e1n", 
    "weight": "65", 
    "first_nationality": "Mexico", 
    "height": "170", 
    "position_wc": "M-L", 
    "team_id": 659, 
    "birth_place": "Zapopan", 
    "id": 53643, 
    "first_name": "Marco", 
    "middle_name": "Jhonfai", 
    "short_name": "Fabi\u00e1n", 
    "real_position": "Attacking Midfielder", 
    "club": "Cruz Azul", 
    "caps": "15", 
    "goals": "5", 
    "real_position_side": "Left/Centre", 
    "jersey_num": "8", 
    "name": "Marco Fabi\u00e1n", 
    "country": "Mexico", 
    "join_date": "2011-06-21", 
    "birth_date": "1989-07-21", 
    "position": "Midfielder"
  }, 
  {
    "first_name": "Isa\u00e1c", 
    "last_name": "Brizuela", 
    "name": "Isa\u00e1c Brizuela", 
    "short_name": "Brizuela", 
    "real_position": "Winger", 
    "club": "Toluca", 
    "country": "Mexico", 
    "first_nationality": "USA", 
    "join_date": "2013-06-28", 
    "weight": "68", 
    "height": "173", 
    "position_wc": null, 
    "team_id": 659, 
    "birth_place": "San Jose", 
    "caps": "7", 
    "birth_date": "1990-08-28", 
    "position": "Midfielder", 
    "real_position_side": "Left/Right", 
    "jersey_num": "17", 
    "id": 72072, 
    "goals": "0"
  }, 
  {
    "last_name": "Lay\u00fan", 
    "weight": "66", 
    "first_nationality": "Mexico", 
    "height": "178", 
    "position_wc": "D-L", 
    "team_id": 659, 
    "birth_place": "Veracruz", 
    "id": 73698, 
    "first_name": "Miguel", 
    "middle_name": "Arturo", 
    "short_name": "Lay\u00fan", 
    "real_position": "Full Back", 
    "club": "Am\u00e9rica", 
    "caps": "13", 
    "goals": "2", 
    "real_position_side": "Left/Right", 
    "jersey_num": "7", 
    "name": "Miguel Lay\u00fan", 
    "country": "Mexico", 
    "join_date": "2013-06-28", 
    "birth_date": "1988-06-25", 
    "position": "Defender"
  }, 
  {
    "last_name": "Pe\u00f1a", 
    "weight": "67", 
    "first_nationality": "Mexico", 
    "height": "175", 
    "position_wc": "F", 
    "team_id": 659, 
    "birth_place": "Ciudad Victoria", 
    "id": 91977, 
    "first_name": "Carlos", 
    "middle_name": "Alberto", 
    "short_name": "Pe\u00f1a", 
    "real_position": "Central Midfielder", 
    "club": "Le\u00f3n", 
    "caps": "16", 
    "goals": "2", 
    "real_position_side": "Centre", 
    "jersey_num": "21", 
    "name": "Carlos Pe\u00f1a", 
    "country": "Mexico", 
    "join_date": "2012-10-04", 
    "birth_date": "1990-03-29", 
    "position": "Midfielder"
  }, 
  {
    "last_name": "Aquino", 
    "weight": "62", 
    "first_nationality": "Mexico", 
    "height": "165", 
    "position_wc": null, 
    "team_id": 659, 
    "birth_place": "Oaxaca de Ju\u00e1rez", 
    "id": 100866, 
    "first_name": "Javier", 
    "middle_name": "Ignacio", 
    "short_name": "Aquino", 
    "real_position": "Winger", 
    "club": "Villarreal", 
    "caps": "22", 
    "goals": "0", 
    "real_position_side": "Right", 
    "jersey_num": "20", 
    "name": "Javier Aquino", 
    "country": "Mexico", 
    "join_date": "2011-06-27", 
    "birth_date": "1990-02-11", 
    "position": "Midfielder"
  }, 
  {
    "last_name": "Reyes", 
    "weight": "66", 
    "first_nationality": "Mexico", 
    "height": "189", 
    "position_wc": null, 
    "team_id": 659, 
    "birth_place": "Mexico City", 
    "id": 100867, 
    "first_name": "Diego", 
    "middle_name": "Antonio", 
    "short_name": "Reyes", 
    "real_position": "Central Defender", 
    "club": "FC Porto", 
    "caps": "14", 
    "goals": "0", 
    "real_position_side": "Centre", 
    "jersey_num": "5", 
    "name": "Diego Reyes", 
    "country": "Mexico", 
    "join_date": "2011-06-27", 
    "birth_date": "1992-09-19", 
    "position": "Defender"
  }, 
  {
    "last_name": "Ponce", 
    "weight": "81", 
    "first_nationality": "USA", 
    "height": "176", 
    "position_wc": null, 
    "team_id": 659, 
    "birth_place": "Sacramento", 
    "id": 100870, 
    "first_name": "Miguel", 
    "middle_name": "\u00c1ngel", 
    "short_name": "Ponce", 
    "real_position": "Full Back", 
    "club": "Toluca", 
    "caps": "6", 
    "goals": "1", 
    "real_position_side": "Left", 
    "jersey_num": "16", 
    "name": "Miguel Ponce", 
    "country": "Mexico", 
    "join_date": "2011-06-27", 
    "birth_date": "1989-04-12", 
    "position": "Defender"
  }, 
  {
    "first_name": "Alan", 
    "last_name": "Pulido", 
    "name": "Alan Pulido", 
    "short_name": "Pulido", 
    "real_position": "Striker", 
    "club": "Tigres", 
    "country": "Mexico", 
    "first_nationality": "Mexico", 
    "join_date": "2011-06-28", 
    "weight": "68", 
    "height": "175", 
    "position_wc": null, 
    "team_id": 659, 
    "birth_place": "Ciudad Victoria", 
    "caps": "6", 
    "birth_date": "1991-03-08", 
    "position": "Forward", 
    "real_position_side": "Centre", 
    "jersey_num": "11", 
    "id": 100987, 
    "goals": "4"
  }, 
  {
    "last_name": "Jim\u00e9nez", 
    "weight": "76", 
    "first_nationality": "Mexico", 
    "height": "186", 
    "position_wc": "F", 
    "team_id": 659, 
    "birth_place": "Tepeji", 
    "id": 102057, 
    "first_name": "Ra\u00fal", 
    "middle_name": "Alonso", 
    "short_name": "Jim\u00e9nez", 
    "real_position": "Striker", 
    "club": "Am\u00e9rica", 
    "caps": "24", 
    "goals": "4", 
    "real_position_side": "Centre", 
    "jersey_num": "9", 
    "name": "Ra\u00fal Jim\u00e9nez", 
    "country": "Mexico", 
    "join_date": "2013-01-20", 
    "birth_date": "1991-05-05", 
    "position": "Forward"
  }, 
  {
    "last_name": "Herrera", 
    "weight": "74", 
    "first_nationality": "Mexico", 
    "height": "180", 
    "position_wc": "M-R", 
    "team_id": 659, 
    "birth_place": "Tijuana", 
    "id": 102578, 
    "first_name": "H\u00e9ctor", 
    "middle_name": "Miguel", 
    "short_name": "Herrera", 
    "real_position": "Central Midfielder", 
    "club": "FC Porto", 
    "caps": "13", 
    "goals": "0", 
    "real_position_side": "Centre", 
    "jersey_num": "6", 
    "name": "H\u00e9ctor Herrera", 
    "country": "Mexico", 
    "join_date": "2012-10-04", 
    "birth_date": "1990-04-19", 
    "position": "Midfielder"
  }, 
  {
    "first_name": "Jos\u00e9 Juan", 
    "last_name": "V\u00e1zquez", 
    "name": "Jos\u00e9 Juan V\u00e1zquez", 
    "short_name": "V\u00e1zquez", 
    "real_position": "Central Midfielder", 
    "club": "Le\u00f3n", 
    "country": "Mexico", 
    "first_nationality": "Mexico", 
    "join_date": "2014-01-23", 
    "weight": "68", 
    "height": "166", 
    "position_wc": "M", 
    "team_id": 659, 
    "birth_place": "Celaya", 
    "caps": "5", 
    "birth_date": "1988-03-14", 
    "position": "Midfielder", 
    "real_position_side": "Left/Centre/Right", 
    "jersey_num": "23", 
    "id": 119772, 
    "goals": "0"
  }
]